Metadata-Version: 2.1
Name: cliete_ajax
Version: 1.1.0
Summary: esta libreria fue creada por IA Sistema de Intres
Home-page: https://www.youtube.com/@IA.Sistema.de.Interes
Author: IA (Sistema de Intres)
Author-email: system.ai.of.interest@gmail.com
Classifier: Programming Language :: Python :: 3
Classifier: License :: OSI Approved :: MIT License
Classifier: Operating System :: OS Independent
Requires-Python: >=3.6
License-File: LICENSE
Requires-Dist: requests
Requires-Dist: tqdm
Requires-Dist: Pillow
Requires-Dist: IPython
